Demo.py
Y3A/Y3A.py
Y3A/__init__.py
Y3A/_version.py
Y3A/icons/AWS.png
Y3A/icons/Arch_AWS-CloudFormation_48.png
Y3A/icons/Arch_AWS-CloudTrail_48.png
Y3A/icons/Arch_AWS-Key-Management-Service_48.png
Y3A/icons/Arch_AWS-Lambda_48.png
Y3A/icons/Arch_Amazon-API-Gateway_48-Resource.png
Y3A/icons/Arch_Amazon-API-Gateway_48.png
Y3A/icons/Arch_Amazon-CloudWatch_48.png
Y3A/icons/Arch_Amazon-DynamoDB_48.png
Y3A/icons/Arch_Amazon-EC2-Auto-Scaling_48.png
Y3A/icons/Arch_Amazon-EC2_48.png
Y3A/icons/Arch_Amazon-Elastic-Container-Registry_48.png
Y3A/icons/Arch_Amazon-Elastic-Container-Service_48.png
Y3A/icons/Arch_Amazon-Elastic-Kubernetes-Service_48.png
Y3A/icons/Arch_Amazon-RDS_48.png
Y3A/icons/Arch_Amazon-Route-53_48.png
Y3A/icons/Arch_Amazon-Simple-Notification-Service_48.png
Y3A/icons/Arch_Amazon-Simple-Storage-Service_48.png
Y3A/icons/Arch_Amazon-Virtual-Private-Cloud_48.png
Y3A/icons/Arch_Elastic-Load-Balancing_48.png
Y3A/icons/EC2_VPCEndpoint.png
Y3A/icons/EC2_VPCPeeringConnection.png
Y3A/icons/ElasticIP.png
Y3A/icons/KeyPair.png
Y3A/icons/NACL.png
Y3A/icons/NATGateWay.png
Y3A/icons/Res_Amazon-EC2_Instance_48.png
Y3A/icons/Route.png
Y3A/icons/RouteTable.png
Y3A/icons/SecurityGroup.png
Y3A/icons/Subnet.png
Y3A/icons/VPCElasticNetworkInterface.png
Y3A/icons/domain_name.png
Y3A/icons/iam_group.png
Y3A/icons/iam_policy.png
Y3A/icons/iam_role.png
Y3A/icons/iam_user.png
Y3A-0.0.10.dist-info/LICENSE
Y3A-0.0.10.dist-info/METADATA
Y3A-0.0.10.dist-info/WHEEL
Y3A-0.0.10.dist-info/top_level.txt
Y3A-0.0.10.dist-info/RECORD
