Metadata-Version: 2.1
Name: Y3A
Version: 0.0.10
Summary: Yet Another AWS Analyser
Author-email: nummulith <nummulith@gmail.com>
License: MIT
Project-URL: Homepage, https://github.com/nummulith/Y3A
Keywords: drawing,graph,graphviz
Classifier: Programming Language :: Python :: 3
Classifier: License :: OSI Approved :: MIT License
Classifier: Operating System :: OS Independent
Requires-Python: >=3.8
License-File: LICENSE
